toggl_api/__about__.py
toggl_api/__init__.py
toggl_api/_client.py
toggl_api/_exceptions.py
toggl_api/_organization.py
toggl_api/_project.py
toggl_api/_tag.py
toggl_api/_tracker.py
toggl_api/_user.py
toggl_api/_workspace.py
toggl_api/config.py
toggl_api/py.typed
toggl_api/reports.py
toggl_api/asyncio/__init__.py
toggl_api/asyncio/_async_cache.py
toggl_api/asyncio/_async_client.py
toggl_api/asyncio/_async_endpoint.py
toggl_api/asyncio/_async_organization.py
toggl_api/asyncio/_async_project.py
toggl_api/asyncio/_async_reports.py
toggl_api/asyncio/_async_sqlite_cache.py
toggl_api/asyncio/_async_tag.py
toggl_api/asyncio/_async_tracker.py
toggl_api/asyncio/_async_user.py
toggl_api/asyncio/_async_workspace.py
toggl_api/meta/__init__.py
toggl_api/meta/_base_endpoint.py
toggl_api/meta/_body.py
toggl_api/meta/_cached_endpoint.py
toggl_api/meta/_enums.py
toggl_api/meta/cache/__init__.py
toggl_api/meta/cache/_base_cache.py
toggl_api/meta/cache/_json_cache.py
toggl_api/meta/cache/_sqlite_cache.py
toggl_api/models/__init__.py
toggl_api/models/_decorators.py
toggl_api/models/_models.py
toggl_api/models/_schema.py
toggl_api/utility/__init__.py
toggl_api/utility/_clean_account.py
toggl_api/utility/_cleanup.py
toggl_api/utility/_generate_fake_data.py
toggl_api/utility/_helpers.py
toggl_api_wrapper-2.2.0.dist-info/METADATA
toggl_api_wrapper-2.2.0.dist-info/WHEEL
toggl_api_wrapper-2.2.0.dist-info/entry_points.txt
toggl_api_wrapper-2.2.0.dist-info/licenses/LICENSE.md
toggl_api_wrapper-2.2.0.dist-info/RECORD
