Metadata-Version: 2.4
Name: toggl-api-wrapper
Version: 2.2.0
Summary: Simple Toggl API wrapper for non-premium features.
Project-URL: Homepage, https://ddkasa.github.io/toggl-api-wrapper/
Project-URL: Documentation, https://ddkasa.github.io/toggl-api-wrapper/api-guide/index.html
Project-URL: Source, https://github.com/ddkasa/toggl-api-wrapper
Project-URL: Bug Tracker, https://github.com/ddkasa/toggl-api-wrapper/issues
Project-URL: Changelog, https://ddkasa.github.io/toggl-api-wrapper/CHANGELOG.html
Project-URL: Coverage, https://app.codecov.io/gh/ddkasa/toggl-api-wrapper
Author-email: David Kasakaitis <davidkasakaitis@proton.me>
Maintainer-email: David Kasakaitis <davidkasakaitis@proton.me>
License-Expression: MIT
License-File: LICENSE.md
Keywords: api,httpx,sqlalchemy,time-tracker,toggl,wrapper
Classifier: Development Status :: 4 - Beta
Classifier: Intended Audience :: Developers
Classifier: License :: OSI Approved :: MIT License
Classifier: Natural Language :: English
Classifier: Programming Language :: Python :: 3
Classifier: Programming Language :: Python :: 3.10
Classifier: Programming Language :: Python :: 3.11
Classifier: Programming Language :: Python :: 3.12
Classifier: Programming Language :: Python :: 3.13
Classifier: Topic :: Internet
Classifier: Topic :: Software Development :: Libraries :: Python Modules
Classifier: Typing :: Typed
Requires-Python: >=3.10
Requires-Dist: httpx>=0.28.1
Provides-Extra: async
Requires-Dist: aiosqlite>=0.20.0; extra == 'async'
Requires-Dist: greenlet>=3.1.1; extra == 'async'
Requires-Dist: sqlalchemy>=2.0.37; extra == 'async'
Provides-Extra: sqlite
Requires-Dist: sqlalchemy>=2.0.37; extra == 'sqlite'
